Metadata-Version: 1.1
Name: vimg
Version: 0.4.3
Summary: An image viewer for the command line
Home-page: http://github.com/jnhansen/vimg
Author: Johannes Hansen
Author-email: johannes.niklas.hansen@gmail.com
License: MIT
Keywords: cli terminal console image picture graphics viewer preview
Platform: UNKNOWN
Classifier: Development Status :: 4 - Beta
Classifier: Environment :: Console
Classifier: Environment :: Console :: Curses
Classifier: Environment :: MacOS X
Classifier: Intended Audience :: Developers
Classifier: Intended Audience :: System Administrators
Classifier: License :: OSI Approved :: MIT License
Classifier: Topic :: Multimedia :: Graphics
Classifier: Topic :: Multimedia :: Graphics :: Viewers
Classifier: Topic :: Utilities
